hivemetastore/__init__.py
hivemetastore/hivemetastore.py
pyhivemetastore-4.1.0rc7.dist-info/METADATA
pyhivemetastore-4.1.0rc7.dist-info/WHEEL
pyhivemetastore-4.1.0rc7.dist-info/entry_points.txt
pyhivemetastore-4.1.0rc7.dist-info/top_level.txt
pyhivemetastore-4.1.0rc7.dist-info/RECORD
