Metadata-Version: 2.4
Name: pyhivemetastore
Version: 4.1.0rc7
Summary: Hive Metastore Standalone
Author-email: Klim Naidenov <pymirror@mail.ru>
Project-URL: Homepage, https://git@git.sourcecraft.dev/pymirror/pyhivemetastore.git
Project-URL: Issues, https://sourcecraft.dev/pymirror/pyhivemetastore/issues
Classifier: Operating System :: OS Independent
Requires-Python: >=3.0
